singer_to_schema/__init__.py
singer_to_schema/cli.py
singer_to_schema/singer_to_schema.py
singer_to_schema-0.2.1.dist-info/WHEEL
singer_to_schema-0.2.1.dist-info/entry_points.txt
singer_to_schema-0.2.1.dist-info/METADATA
singer_to_schema-0.2.1.dist-info/RECORD
