Metadata-Version: 2.3
Name: singer-to-schema
Version: 0.2.1
Summary: A CLI and library to convert Singer catalogs to data warehouse schemas
Author: Andrew Jones
Author-email: Andrew Jones <andrew@andrew-jones.com>
License: MIT License
Requires-Dist: pytest>=7.0.0 ; extra == 'dev'
Requires-Python: >=3.8
Project-URL: Homepage, https://github.com/andrew-jones/singer-to-schema
Project-URL: Repository, https://github.com/andrew-jones/singer-to-schema
Provides-Extra: dev
